{
  "generatedAt": "2025-12-25T10:02:07.889Z",
  "osmRelation": "https://www.openstreetmap.org/relation/2052885",
  "stations": [
    {
      "osmNodeId": "7160108921",
      "nameLocalRaw": "杭州东",
      "nameLocal": "杭州东",
      "nameRomaji": "Hangzhoudong",
      "nameEnglish": "Hangzhoudong",
      "location": {
        "latitude": 30.2935486,
        "longitude": 120.2082034
      },
      "hasPassengerService": true
    },
    {
      "osmNodeId": "7039952242",
      "nameLocalRaw": "杭州南",
      "nameLocal": "杭州南",
      "nameRomaji": "Hangzhounan",
      "nameEnglish": "Hangzhounan",
      "location": {
        "latitude": 30.1746889,
        "longitude": 120.2900497
      },
      "hasPassengerService": true
    },
    {
      "osmNodeId": "7714110165",
      "nameLocalRaw": "杭甬杭州南线路所",
      "nameLocal": "杭甬杭州南所",
      "nameRomaji": "杭甬杭州南所",
      "nameEnglish": "杭甬杭州南所",
      "location": {
        "latitude": 30.140284,
        "longitude": 120.3193756
      },
      "hasPassengerService": true
    },
    {
      "osmNodeId": "7714110164",
      "nameLocalRaw": "绍兴北",
      "nameLocal": "绍兴北",
      "nameRomaji": "Shaoxingbei",
      "nameEnglish": "Shaoxingbei",
      "location": {
        "latitude": 30.101974,
        "longitude": 120.5344391
      },
      "hasPassengerService": true
    },
    {
      "osmNodeId": "5382282762",
      "nameLocalRaw": "绍兴东",
      "nameLocal": "绍兴东",
      "nameRomaji": "Shaoxingdong",
      "nameEnglish": "Shaoxingdong",
      "location": {
        "latitude": 30.057183,
        "longitude": 120.8489935
      },
      "hasPassengerService": true
    },
    {
      "osmNodeId": "7714110163",
      "nameLocalRaw": "余姚北",
      "nameLocal": "余姚北",
      "nameRomaji": "Yuyaobei",
      "nameEnglish": "Yuyaobei",
      "location": {
        "latitude": 30.1008272,
        "longitude": 121.1637121
      },
      "hasPassengerService": true
    },
    {
      "osmNodeId": "7714110162",
      "nameLocalRaw": "庄桥",
      "nameLocal": "庄桥",
      "nameRomaji": "Zhuangqiao",
      "nameEnglish": "Zhuangqiao",
      "location": {
        "latitude": 29.9261417,
        "longitude": 121.531325
      },
      "hasPassengerService": true
    },
    {
      "osmNodeId": "7714110161",
      "nameLocalRaw": "宁波",
      "nameLocal": "宁波",
      "nameRomaji": "Ningbo",
      "nameEnglish": "Ningbo",
      "location": {
        "latitude": 29.8646327,
        "longitude": 121.5326567
      },
      "hasPassengerService": true
    },
    {
      "osmNodeId": "7686886385",
      "nameLocalRaw": "宁波东",
      "nameLocal": "宁波东",
      "nameRomaji": "Ningbodong",
      "nameEnglish": "Ningbodong",
      "location": {
        "latitude": 29.8508571,
        "longitude": 121.5809942
      },
      "hasPassengerService": true
    },
    {
      "osmNodeId": "7687112643",
      "nameLocalRaw": "云龙",
      "nameLocal": "云龙",
      "nameRomaji": "Yunlong",
      "nameEnglish": "Yunlong",
      "location": {
        "latitude": 29.7764736,
        "longitude": 121.5880201
      },
      "hasPassengerService": true
    },
    {
      "osmNodeId": "7714110160",
      "nameLocalRaw": "奉化",
      "nameLocal": "奉化",
      "nameRomaji": "Fenghua",
      "nameEnglish": "Fenghua",
      "location": {
        "latitude": 29.6304914,
        "longitude": 121.460225
      },
      "hasPassengerService": true
    },
    {
      "osmNodeId": "7714110159",
      "nameLocalRaw": "宁海",
      "nameLocal": "宁海",
      "nameRomaji": "Ninghai",
      "nameEnglish": "Ninghai",
      "location": {
        "latitude": 29.3393268,
        "longitude": 121.4149413
      },
      "hasPassengerService": true
    },
    {
      "osmNodeId": "7714110158",
      "nameLocalRaw": "三门县",
      "nameLocal": "三门县",
      "nameRomaji": "Sanmenxian",
      "nameEnglish": "Sanmenxian",
      "location": {
        "latitude": 29.057886,
        "longitude": 121.3587785
      },
      "hasPassengerService": true
    },
    {
      "osmNodeId": "7714110157",
      "nameLocalRaw": "临海",
      "nameLocal": "临海",
      "nameRomaji": "Linhai",
      "nameEnglish": "Linhai",
      "location": {
        "latitude": 28.8830234,
        "longitude": 121.2424833
      },
      "hasPassengerService": true
    },
    {
      "osmNodeId": "7714110156",
      "nameLocalRaw": "台州西",
      "nameLocal": "台州西",
      "nameRomaji": "Taizhouxi",
      "nameEnglish": "Taizhouxi",
      "location": {
        "latitude": 28.6891529,
        "longitude": 121.286474
      },
      "hasPassengerService": true
    },
    {
      "osmNodeId": "7714110155",
      "nameLocalRaw": "台州南",
      "nameLocal": "台州南",
      "nameRomaji": "Taizhounan",
      "nameEnglish": "Taizhounan",
      "location": {
        "latitude": 28.5422642,
        "longitude": 121.3185292
      },
      "hasPassengerService": true
    },
    {
      "osmNodeId": "7714110154",
      "nameLocalRaw": "温岭",
      "nameLocal": "温岭",
      "nameRomaji": "Wenling",
      "nameEnglish": "Wenling",
      "location": {
        "latitude": 28.4821963,
        "longitude": 121.3208306
      },
      "hasPassengerService": true
    },
    {
      "osmNodeId": "7714110153",
      "nameLocalRaw": "雁荡山",
      "nameLocal": "雁荡山",
      "nameRomaji": "Yandangshan",
      "nameEnglish": "Yandangshan",
      "location": {
        "latitude": 28.3444955,
        "longitude": 121.1478227
      },
      "hasPassengerService": true
    },
    {
      "osmNodeId": "7714110152",
      "nameLocalRaw": "乐清东",
      "nameLocal": "乐清东",
      "nameRomaji": "Yueqingdong",
      "nameEnglish": "Yueqingdong",
      "location": {
        "latitude": 28.2002762,
        "longitude": 120.9874964
      },
      "hasPassengerService": true
    },
    {
      "osmNodeId": "7714110151",
      "nameLocalRaw": "乐清",
      "nameLocal": "乐清",
      "nameRomaji": "Yueqing",
      "nameEnglish": "Yueqing",
      "location": {
        "latitude": 28.0877033,
        "longitude": 120.8555424
      },
      "hasPassengerService": true
    },
    {
      "osmNodeId": "7714110150",
      "nameLocalRaw": "温州北",
      "nameLocal": "温州北",
      "nameRomaji": "Wenzhoubei",
      "nameEnglish": "Wenzhoubei",
      "location": {
        "latitude": 28.0710301,
        "longitude": 120.6913314
      },
      "hasPassengerService": true
    },
    {
      "osmNodeId": "7693453988",
      "nameLocalRaw": "温州南",
      "nameLocal": "温州南",
      "nameRomaji": "Wenzhounan",
      "nameEnglish": "Wenzhounan",
      "location": {
        "latitude": 27.9692843,
        "longitude": 120.5816138
      },
      "hasPassengerService": true
    },
    {
      "osmNodeId": "7693453987",
      "nameLocalRaw": "瓯海",
      "nameLocal": "瓯海",
      "nameRomaji": "Ouhai",
      "nameEnglish": "Ouhai",
      "location": {
        "latitude": 27.9311971,
        "longitude": 120.5718559
      },
      "hasPassengerService": true
    },
    {
      "osmNodeId": "7714110149",
      "nameLocalRaw": "瑞安北",
      "nameLocal": "瑞安北",
      "nameRomaji": "Rui'anbei",
      "nameEnglish": "Rui'anbei",
      "location": {
        "latitude": 27.8294937,
        "longitude": 120.5906796
      },
      "hasPassengerService": true
    },
    {
      "osmNodeId": "7714110148",
      "nameLocalRaw": "瑞安",
      "nameLocal": "瑞安",
      "nameRomaji": "Rui'an",
      "nameEnglish": "Rui'an",
      "location": {
        "latitude": 27.7699263,
        "longitude": 120.5770218
      },
      "hasPassengerService": true
    },
    {
      "osmNodeId": "7714110147",
      "nameLocalRaw": "平阳",
      "nameLocal": "平阳",
      "nameRomaji": "Pingyang",
      "nameEnglish": "Pingyang",
      "location": {
        "latitude": 27.629223,
        "longitude": 120.5408442
      },
      "hasPassengerService": true
    },
    {
      "osmNodeId": "7714110146",
      "nameLocalRaw": "苍南",
      "nameLocal": "苍南",
      "nameRomaji": "苍南",
      "nameEnglish": "苍南",
      "location": {
        "latitude": 27.5313093,
        "longitude": 120.40836
      },
      "hasPassengerService": true
    },
    {
      "osmNodeId": "2479269524",
      "nameLocalRaw": "福鼎",
      "nameLocal": "福鼎",
      "nameRomaji": "Fuding",
      "nameEnglish": "Fuding",
      "location": {
        "latitude": 27.2855804,
        "longitude": 120.1846007
      },
      "hasPassengerService": true
    },
    {
      "osmNodeId": "7714110145",
      "nameLocalRaw": "太姥山",
      "nameLocal": "太姥山",
      "nameRomaji": "Taimushan",
      "nameEnglish": "Taimushan",
      "location": {
        "latitude": 27.1298827,
        "longitude": 120.2197409
      },
      "hasPassengerService": true
    },
    {
      "osmNodeId": "5617318079",
      "nameLocalRaw": "霞浦",
      "nameLocal": "霞浦",
      "nameRomaji": "Xiapu",
      "nameEnglish": "Xiapu",
      "location": {
        "latitude": 26.9127474,
        "longitude": 120.0282365
      },
      "hasPassengerService": true
    },
    {
      "osmNodeId": "5099753623",
      "nameLocalRaw": "福安",
      "nameLocal": "福安",
      "nameRomaji": "Fuan",
      "nameEnglish": "Fuan",
      "location": {
        "latitude": 26.8374358,
        "longitude": 119.7128302
      },
      "hasPassengerService": true
    },
    {
      "osmNodeId": "5614557340",
      "nameLocalRaw": "宁德",
      "nameLocal": "宁德",
      "nameRomaji": "Ningde",
      "nameEnglish": "Ningde",
      "location": {
        "latitude": 26.6729441,
        "longitude": 119.5793795
      },
      "hasPassengerService": true
    },
    {
      "osmNodeId": "1895255830",
      "nameLocalRaw": "罗源",
      "nameLocal": "罗源",
      "nameRomaji": "Luoyuan",
      "nameEnglish": "Luoyuan",
      "location": {
        "latitude": 26.4591921,
        "longitude": 119.5721077
      },
      "hasPassengerService": true
    },
    {
      "osmNodeId": "4254005158",
      "nameLocalRaw": "透堡",
      "nameLocal": "透堡",
      "nameRomaji": "Toubao",
      "nameEnglish": "Toubao",
      "location": {
        "latitude": 26.3429337,
        "longitude": 119.6160026
      },
      "hasPassengerService": true
    },
    {
      "osmNodeId": "7713944581",
      "nameLocalRaw": "连江",
      "nameLocal": "连江",
      "nameRomaji": "Lianjiang",
      "nameEnglish": "Lianjiang",
      "location": {
        "latitude": 26.1977359,
        "longitude": 119.5627016
      },
      "hasPassengerService": true
    },
    {
      "osmNodeId": "3694585921",
      "nameLocalRaw": "温福线路所",
      "nameLocal": "温福所",
      "nameRomaji": "温福所",
      "nameEnglish": "温福所",
      "location": {
        "latitude": 26.0389057,
        "longitude": 119.4023902
      },
      "hasPassengerService": true
    },
    {
      "osmNodeId": "3694585922",
      "nameLocalRaw": "福厦线路所",
      "nameLocal": "福厦所",
      "nameRomaji": "福厦所",
      "nameEnglish": "福厦所",
      "location": {
        "latitude": 26.0252565,
        "longitude": 119.381629
      },
      "hasPassengerService": true
    },
    {
      "osmNodeId": "7719582540",
      "nameLocalRaw": "福州南",
      "nameLocal": "福州南",
      "nameRomaji": "Fuzhounan",
      "nameEnglish": "Fuzhounan",
      "location": {
        "latitude": 25.9892567,
        "longitude": 119.3866957
      },
      "hasPassengerService": true
    },
    {
      "osmNodeId": "1878843430",
      "nameLocalRaw": "福清",
      "nameLocal": "福清",
      "nameRomaji": "Fuqing",
      "nameEnglish": "Fuqing",
      "location": {
        "latitude": 25.678311,
        "longitude": 119.3794399
      },
      "hasPassengerService": true
    },
    {
      "osmNodeId": "5175887684",
      "nameLocalRaw": "渔溪",
      "nameLocal": "渔溪",
      "nameRomaji": "Yuxi",
      "nameEnglish": "Yuxi",
      "location": {
        "latitude": 25.5755628,
        "longitude": 119.2911896
      },
      "hasPassengerService": true
    },
    {
      "osmNodeId": "7792857871",
      "nameLocalRaw": "涵江",
      "nameLocal": "涵江",
      "nameRomaji": "涵江",
      "nameEnglish": "涵江",
      "location": {
        "latitude": 25.4944032,
        "longitude": 119.1708416
      },
      "hasPassengerService": true
    },
    {
      "osmNodeId": "1879551033",
      "nameLocalRaw": "莆田",
      "nameLocal": "莆田",
      "nameRomaji": "Putian",
      "nameEnglish": "Putian",
      "location": {
        "latitude": 25.3538682,
        "longitude": 119.0570588
      },
      "hasPassengerService": true
    },
    {
      "osmNodeId": "3365981115",
      "nameLocalRaw": "仙游",
      "nameLocal": "仙游",
      "nameRomaji": "Xianyou",
      "nameEnglish": "Xianyou",
      "location": {
        "latitude": 25.2535131,
        "longitude": 118.8666649
      },
      "hasPassengerService": true
    },
    {
      "osmNodeId": "3378402906",
      "nameLocalRaw": "惠安",
      "nameLocal": "惠安",
      "nameRomaji": "Hui'an",
      "nameEnglish": "Hui'an",
      "location": {
        "latitude": 25.0606368,
        "longitude": 118.7096977
      },
      "hasPassengerService": true
    },
    {
      "osmNodeId": "1879551038",
      "nameLocalRaw": "泉州",
      "nameLocal": "泉州",
      "nameRomaji": "Quanzhou",
      "nameEnglish": "Quanzhou",
      "location": {
        "latitude": 24.9759459,
        "longitude": 118.5632413
      },
      "hasPassengerService": true
    },
    {
      "osmNodeId": "7778190320",
      "nameLocalRaw": "晋江",
      "nameLocal": "晋江",
      "nameRomaji": "Jinjiang",
      "nameEnglish": "Jinjiang",
      "location": {
        "latitude": 24.7974067,
        "longitude": 118.4541454
      },
      "hasPassengerService": true
    },
    {
      "osmNodeId": "5175876234",
      "nameLocalRaw": "翔安",
      "nameLocal": "翔安",
      "nameRomaji": "Xiang'an",
      "nameEnglish": "Xiang'an",
      "location": {
        "latitude": 24.6893505,
        "longitude": 118.2641423
      },
      "hasPassengerService": true
    },
    {
      "osmNodeId": "6527623010",
      "nameLocalRaw": "厦门北",
      "nameLocal": "厦门北",
      "nameRomaji": "Xiamen North",
      "nameEnglish": "Xiamen North",
      "location": {
        "latitude": 24.6397375,
        "longitude": 118.0686353
      },
      "hasPassengerService": true
    },
    {
      "osmNodeId": "3694551474",
      "nameLocalRaw": "前场",
      "nameLocal": "前场",
      "nameRomaji": "Qianchang",
      "nameEnglish": "Qianchang",
      "location": {
        "latitude": 24.5728722,
        "longitude": 117.9730668
      },
      "hasPassengerService": true
    },
    {
      "osmNodeId": "2481375096",
      "nameLocalRaw": "角美",
      "nameLocal": "角美",
      "nameRomaji": "Jiaomei",
      "nameEnglish": "Jiaomei",
      "location": {
        "latitude": 24.5295661,
        "longitude": 117.8754377
      },
      "hasPassengerService": true
    },
    {
      "osmNodeId": "5100559665",
      "nameLocalRaw": "漳州",
      "nameLocal": "漳州",
      "nameRomaji": "Zhangzhou Railway Station",
      "nameEnglish": "Zhangzhou Railway Station",
      "location": {
        "latitude": 24.4598069,
        "longitude": 117.7113175
      },
      "hasPassengerService": true
    },
    {
      "osmNodeId": "9258885993",
      "nameLocalRaw": "漳浦",
      "nameLocal": "漳浦",
      "nameRomaji": "Zhangpu",
      "nameEnglish": "Zhangpu",
      "location": {
        "latitude": 24.0991136,
        "longitude": 117.5581513
      },
      "hasPassengerService": true
    },
    {
      "osmNodeId": "9258885992",
      "nameLocalRaw": "云霄",
      "nameLocal": "云霄",
      "nameRomaji": "Yunxiao",
      "nameEnglish": "Yunxiao",
      "location": {
        "latitude": 23.893835,
        "longitude": 117.3568609
      },
      "hasPassengerService": true
    },
    {
      "osmNodeId": "2990496476",
      "nameLocalRaw": "诏安",
      "nameLocal": "诏安",
      "nameRomaji": "Zhao'an",
      "nameEnglish": "Zhao'an",
      "location": {
        "latitude": 23.774602,
        "longitude": 117.0926958
      },
      "hasPassengerService": true
    },
    {
      "osmNodeId": "9258885991",
      "nameLocalRaw": "饶平",
      "nameLocal": "饶平",
      "nameRomaji": "Raoping",
      "nameEnglish": "Raoping",
      "location": {
        "latitude": 23.714094,
        "longitude": 116.9283432
      },
      "hasPassengerService": true
    },
    {
      "osmNodeId": "8475736019",
      "nameLocalRaw": "韩江桥线路所",
      "nameLocal": "韩江桥所",
      "nameRomaji": "韩江桥所",
      "nameEnglish": "韩江桥所",
      "location": {
        "latitude": 23.5657472,
        "longitude": 116.6497858
      },
      "hasPassengerService": true
    },
    {
      "osmNodeId": "5951170198",
      "nameLocalRaw": "潮汕",
      "nameLocal": "潮汕",
      "nameRomaji": "Chaoshan",
      "nameEnglish": "Chaoshan",
      "location": {
        "latitude": 23.5424042,
        "longitude": 116.5828304
      },
      "hasPassengerService": true
    },
    {
      "osmNodeId": "10555760577",
      "nameLocalRaw": "普宁",
      "nameLocal": "普宁",
      "nameRomaji": "Puning",
      "nameEnglish": "Puning",
      "location": {
        "latitude": 23.2694032,
        "longitude": 116.194641
      },
      "hasPassengerService": true
    },
    {
      "osmNodeId": "2832361211",
      "nameLocalRaw": "潮阳",
      "nameLocal": "潮阳",
      "nameRomaji": "Chaoyang",
      "nameEnglish": "Chaoyang",
      "location": {
        "latitude": 23.3833607,
        "longitude": 116.4173818
      },
      "hasPassengerService": true
    },
    {
      "osmNodeId": "2990496474",
      "nameLocalRaw": "葵潭",
      "nameLocal": "葵潭",
      "nameRomaji": "Kuitan",
      "nameEnglish": "Kuitan",
      "location": {
        "latitude": 23.0670446,
        "longitude": 115.9921558
      },
      "hasPassengerService": true
    },
    {
      "osmNodeId": "1732278092",
      "nameLocalRaw": "陆丰",
      "nameLocal": "陆丰",
      "nameRomaji": "Lufeng",
      "nameEnglish": "Lufeng",
      "location": {
        "latitude": 22.9507378,
        "longitude": 115.7284621
      },
      "hasPassengerService": true
    },
    {
      "osmNodeId": "2719758936",
      "nameLocalRaw": "汕尾",
      "nameLocal": "汕尾",
      "nameRomaji": "Shanwei",
      "nameEnglish": "Shanwei",
      "location": {
        "latitude": 22.8132068,
        "longitude": 115.4237222
      },
      "hasPassengerService": true
    },
    {
      "osmNodeId": "10224522918",
      "nameLocalRaw": "鲘门",
      "nameLocal": "鲘门",
      "nameRomaji": "Houmen",
      "nameEnglish": "Houmen",
      "location": {
        "latitude": 22.8156414,
        "longitude": 115.1202422
      },
      "hasPassengerService": true
    },
    {
      "osmNodeId": "2719758932",
      "nameLocalRaw": "惠东南",
      "nameLocal": "惠东南",
      "nameRomaji": "Huidongnan",
      "nameEnglish": "Huidongnan",
      "location": {
        "latitude": 22.8475822,
        "longitude": 114.7897316
      },
      "hasPassengerService": true
    },
    {
      "osmNodeId": "2719758933",
      "nameLocalRaw": "惠阳",
      "nameLocal": "惠阳",
      "nameRomaji": "Huiyang",
      "nameEnglish": "Huiyang",
      "location": {
        "latitude": 22.7866481,
        "longitude": 114.4879114
      },
      "hasPassengerService": true
    },
    {
      "osmNodeId": "6708684808",
      "nameLocalRaw": "深圳坪山",
      "nameLocal": "深圳坪山",
      "nameRomaji": "Shenzhenpingshan",
      "nameEnglish": "Shenzhenpingshan",
      "location": {
        "latitude": 22.7103736,
        "longitude": 114.3221962
      },
      "hasPassengerService": true
    },
    {
      "osmNodeId": "9259028979",
      "nameLocalRaw": "李朗线路所",
      "nameLocal": "李朗所",
      "nameRomaji": "李朗所",
      "nameEnglish": "李朗所",
      "location": {
        "latitude": 22.6403034,
        "longitude": 114.1526699
      },
      "hasPassengerService": true
    },
    {
      "osmNodeId": "5369745039",
      "nameLocalRaw": "深圳北",
      "nameLocal": "深圳北",
      "nameRomaji": "Shenzhen North",
      "nameEnglish": "Shenzhen North",
      "location": {
        "latitude": 22.6120365,
        "longitude": 114.0239469
      },
      "hasPassengerService": true
    }
  ]
}